mapflpy-1.1.2.dist-info/RECORD
mapflpy-1.1.2.dist-info/WHEEL
mapflpy-1.1.2.dist-info/METADATA
mapflpy-1.1.2.dist-info/licenses/LICENSE.txt
mapflpy/_version.py
mapflpy/globals.py
mapflpy/__init__.py
mapflpy/utils.py
mapflpy/py.typed
mapflpy/scripts.py
mapflpy/tracer.py
mapflpy/data.py
mapflpy/.dylibs/libcom_err.3.0.dylib
mapflpy/.dylibs/libhdf5_fortran.310.dylib
mapflpy/.dylibs/libssh2.1.0.1.dylib
mapflpy/.dylibs/libssl.3.dylib
mapflpy/.dylibs/libcrypto.3.dylib
mapflpy/.dylibs/libhdf5.310.dylib
mapflpy/.dylibs/libgssapi_krb5.2.2.dylib
mapflpy/.dylibs/libgfortran.5.dylib
mapflpy/.dylibs/libz.1.3.1.dylib
mapflpy/.dylibs/libhdf5_hl.310.dylib
mapflpy/.dylibs/libsz.2.0.1.dylib
mapflpy/.dylibs/libnghttp2.14.dylib
mapflpy/.dylibs/libkrb5.3.3.dylib
mapflpy/.dylibs/libcurl.4.dylib
mapflpy/.dylibs/libhdf5hl_fortran.310.dylib
mapflpy/.dylibs/libkrb5support.1.1.dylib
mapflpy/.dylibs/libk5crypto.3.1.dylib
mapflpy/.dylibs/libquadmath.0.dylib
mapflpy/.dylibs/libgcc_s.1.1.dylib
mapflpy/.dylibs/libzstd.1.5.7.dylib
mapflpy/fortran/__init__.py
mapflpy/fortran/mapflpy_fortran.cpython-311-darwin.so
